aio/api/github/__init__.py
aio/api/github/api.py
aio/api/github/exceptions.py
aio/api/github/interface.py
aio/api/github/py.typed
aio/api/github/typing.py
aio/api/github/utils.py
aio/api/github/abstract/__init__.py
aio/api/github/abstract/api.py
aio/api/github/abstract/base.py
aio/api/github/abstract/commit.py
aio/api/github/abstract/iterator.py
aio/api/github/abstract/label.py
aio/api/github/abstract/release.py
aio/api/github/abstract/repo.py
aio/api/github/abstract/tag.py
aio/api/github/abstract/actions/__init__.py
aio/api/github/abstract/actions/actions.py
aio/api/github/abstract/issues/__init__.py
aio/api/github/abstract/issues/issues.py
aio/api/github/abstract/issues/tracker.py
aio.api.github-0.2.10.dist-info/METADATA
aio.api.github-0.2.10.dist-info/WHEEL
aio.api.github-0.2.10.dist-info/namespace_packages.txt
aio.api.github-0.2.10.dist-info/top_level.txt
aio.api.github-0.2.10.dist-info/RECORD
