Metadata-Version: 2.1
Name: aio.api.github
Version: 0.2.10
Summary: Wrapper around gidgethub
Home-page: https://github.com/envoyproxy/toolshed/tree/main/aio.api.github
Author: Ryan Northey
Author-email: ryan@synca.io
Maintainer: Ryan Northey
Maintainer-email: ryan@synca.io
License: Apache Software License 2.0
Requires-Python: >=3.10.0
Requires-Dist: abstracts (>=0.0.12)
Requires-Dist: aio.core (>=0.10.5)
Requires-Dist: aiohttp (>=3.8.1)
Requires-Dist: gidgethub
Requires-Dist: packaging (>=23.0)
